setup.py
contendo_utils/ProUtils.py
contendo_utils/__init__.py
contendo_utils/bigquery_gcs_utils.py
contendo_utils/contendo_configuration_manager.py
contendo_utils/contendo_logging.py
contendo_utils/dict_to_object.py
contendo_utils/producer_consumers_engine.py
contendo_utils/producer_consumers_engine_threads.py
contendo_utils/simple_text_interaction.py
contendo_utils/utils.py
contendo_utils.egg-info/PKG-INFO
contendo_utils.egg-info/SOURCES.txt
contendo_utils.egg-info/dependency_links.txt
contendo_utils.egg-info/not-zip-safe
contendo_utils.egg-info/requires.txt
contendo_utils.egg-info/top_level.txt