Metadata-Version: 1.0
Name: contendo-utils
Version: 0.3.1
Summary: General python and google-cloud related utilities
Home-page: https://github.com/Yahalis/contendo_core1/tree/master/contendo_utils
Author: Yahali Sherman, contendo.ai
Author-email: yahali@contendo.ai
License: MIT
Platform: UNKNOWN
